<?xml version='1.0' encoding='UTF-8'?>
<Dictionary xmlns="http://www.opengis.net/gml/3.2" xmlns:xsi="http://www.w3.org/2001/XMLSchema-instance" gml:id="RockOutcropsCoverValue" xmlns:gml="http://www.opengis.net/gml/3.2" xsi:schemaLocation="http://www.opengis.net/gml/3.2 http://schemas.opengis.net/gml/3.2.1/gml.xsd">
  <identifier codeSpace="http://www.fao.org/global-soil-partnership/dictionary/RockOutcropsCoverValue.xml">Recommended classification of rock outcrops</identifier>
  <dictionaryEntry>
    <Definition gml:id="RockOutcropsCoverValue_N">
      <description>None</description>
      <identifier codeSpace="http://www.fao.org/global-soil-partnership/dictionary/RockOutcropsCoverValue.xml">N</identifier>
    </Definition>
  </dictionaryEntry>
  <dictionaryEntry>
    <Definition gml:id="RockOutcropsCoverValue_V">
      <description>Very few</description>
      <identifier codeSpace="http://www.fao.org/global-soil-partnership/dictionary/RockOutcropsCoverValue.xml">V</identifier>
    </Definition>
  </dictionaryEntry>
  <dictionaryEntry>
    <Definition gml:id="RockOutcropsCoverValue_F">
      <description>Few</description>
      <identifier codeSpace="http://www.fao.org/global-soil-partnership/dictionary/RockOutcropsCoverValue.xml">F</identifier>
    </Definition>
  </dictionaryEntry>
  <dictionaryEntry>
    <Definition gml:id="RockOutcropsCoverValue_C">
      <description>Common</description>
      <identifier codeSpace="http://www.fao.org/global-soil-partnership/dictionary/RockOutcropsCoverValue.xml">C</identifier>
    </Definition>
  </dictionaryEntry>
  <dictionaryEntry>
    <Definition gml:id="RockOutcropsCoverValue_M">
      <description>Many</description>
      <identifier codeSpace="http://www.fao.org/global-soil-partnership/dictionary/RockOutcropsCoverValue.xml">M</identifier>
    </Definition>
  </dictionaryEntry>
  <dictionaryEntry>
    <Definition gml:id="RockOutcropsCoverValue_A">
      <description>Abundant</description>
      <identifier codeSpace="http://www.fao.org/global-soil-partnership/dictionary/RockOutcropsCoverValue.xml">A</identifier>
    </Definition>
  </dictionaryEntry>
  <dictionaryEntry>
    <Definition gml:id="RockOutcropsCoverValue_D">
      <description>Dominant</description>
      <identifier codeSpace="http://www.fao.org/global-soil-partnership/dictionary/RockOutcropsCoverValue.xml">D</identifier>
    </Definition>
  </dictionaryEntry>
</Dictionary>
